threepio/__init__.py
threepio/version.py
threepio-0.2.dist-info/DESCRIPTION.rst
threepio-0.2.dist-info/METADATA
threepio-0.2.dist-info/metadata.json
threepio-0.2.dist-info/RECORD
threepio-0.2.dist-info/top_level.txt
threepio-0.2.dist-info/WHEEL
