Metadata-Version: 2.0
Name: threepio
Version: 0.2
Summary: Minimally improved noise for python. Pragmatic, minimalimproved logging for python.
Home-page: https://github.com/jmatt/threepio
Author: jmatt
Author-email: jmatt@jmatt.org
License: Apache License, Version 2.0
Platform: UNKNOWN
Classifier: Development Status :: 4 - Beta
Classifier: Intended Audience :: Developers
Classifier: Intended Audience :: Information Technology
Classifier: License :: OSI Approved :: Apache Software License
Classifier: Operating System :: OS Independent
Classifier: Programming Language :: Python
Classifier: Topic :: Software Development :: Libraries
Classifier: Topic :: System :: Logging
